<?xml version="1.0" encoding="utf-8"?>
<!-- Created by ModBuddy on 6/8/2013 11:22:10 PM -->
<GameData>
	<Civilizations>
		<Update>
			<Where Type="CIVILIZATION_AMERICA"/>
			<Set AIPlayable="false" Playable="false"/>
		</Update>
		<Update>
			<Where Type="CIVILIZATION_ARABIA"/>
			<Set AIPlayable="false" Playable="false"/>
		</Update>
		<Update>
			<Where Type="CIVILIZATION_AZTEC"/>
			<Set AIPlayable="false" Playable="false"/>
		</Update>
		<Update>
			<Where Type="CIVILIZATION_CHINA"/>
			<Set AIPlayable="false" Playable="false"/>
		</Update>
		<Update>
			<Where Type="CIVILIZATION_EGYPT"/>
			<Set AIPlayable="false" Playable="false"/>
		</Update>
		<Update>
			<Where Type="CIVILIZATION_ENGLAND"/>
			<Set AIPlayable="false" Playable="false"/>
		</Update>
		<Update>
			<Where Type="CIVILIZATION_FRANCE"/>
			<Set AIPlayable="false" Playable="false"/>
		</Update>
		<Update>
			<Where Type="CIVILIZATION_GERMANY"/>
			<Set AIPlayable="false" Playable="false"/>
		</Update>
		<Update>
			<Where Type="CIVILIZATION_GREECE"/>
			<Set AIPlayable="false" Playable="false"/>
		</Update>
		<Update>
			<Where Type="CIVILIZATION_INDIA"/>
			<Set AIPlayable="false" Playable="false"/>
		</Update>
		<Update>
			<Where Type="CIVILIZATION_IROQUOIS"/>
			<Set AIPlayable="false" Playable="false"/>
		</Update>
		<Update>
			<Where Type="CIVILIZATION_JAPAN"/>
			<Set AIPlayable="false" Playable="false"/>
		</Update>
		<Update>
			<Where Type="CIVILIZATION_OTTOMAN"/>
			<Set AIPlayable="false" Playable="false"/>
		</Update>
		<Update>
			<Where Type="CIVILIZATION_PERSIA"/>
			<Set AIPlayable="false" Playable="false"/>
		</Update>
		<Update>
			<Where Type="CIVILIZATION_ROME"/>
			<Set AIPlayable="false" Playable="false"/>
		</Update>
		<Update>
			<Where Type="CIVILIZATION_RUSSIA"/>
			<Set AIPlayable="false" Playable="false"/>
		</Update>
		<Update>
			<Where Type="CIVILIZATION_SIAM"/>
			<Set AIPlayable="false" Playable="false"/>
		</Update>
		<Update>
			<Where Type="CIVILIZATION_SONGHAI"/>
			<Set AIPlayable="false" Playable="false"/>
		</Update>
		<Update>
			<Where Type="CIVILIZATION_MONGOL"/>
			<Set AIPlayable="false" Playable="false"/>
		</Update>
		<Update>
			<Where Type="CIVILIZATION_INCA"/>
			<Set AIPlayable="false" Playable="false"/>
		</Update>
		<Update>
			<Where Type="CIVILIZATION_SPAIN"/>
			<Set AIPlayable="false" Playable="false"/>
		</Update>
		<Update>
			<Where Type="CIVILIZATION_POLYNESIA"/>
			<Set AIPlayable="false" Playable="false"/>
		</Update>
		<Update>
			<Where Type="CIVILIZATION_DENMARK"/>
			<Set AIPlayable="false" Playable="false"/>
		</Update>
		<Update>
			<Where Type="CIVILIZATION_KOREA"/>
			<Set AIPlayable="false" Playable="false"/>
		</Update>
		<Update>
			<Where Type="CIVILIZATION_BABYLON"/>
			<Set AIPlayable="false" Playable="false"/>
		</Update>
		<Update>
			<Where Type="CIVILIZATION_AUSTRIA"/>
			<Set AIPlayable="false" Playable="false"/>
		</Update>
		<Update>
			<Where Type="CIVILIZATION_BYZANTIUM"/>
			<Set AIPlayable="false" Playable="false"/>
		</Update>
		<Update>
			<Where Type="CIVILIZATION_CARTHAGE"/>
			<Set AIPlayable="false" Playable="false"/>
		</Update>
		<Update>
			<Where Type="CIVILIZATION_CELTS"/>
			<Set AIPlayable="false" Playable="false"/>
		</Update>
		<Update>
			<Where Type="CIVILIZATION_ETHIOPIA"/>
			<Set AIPlayable="false" Playable="false"/>
		</Update>
		<Update>
			<Where Type="CIVILIZATION_HUNS"/>
			<Set AIPlayable="false" Playable="false"/>
		</Update>
		<Update>
			<Where Type="CIVILIZATION_MAYA"/>
			<Set AIPlayable="false" Playable="false"/>
		</Update>
		<Update>
			<Where Type="CIVILIZATION_NETHERLANDS"/>
			<Set AIPlayable="false" Playable="false"/>
		</Update>
		<Update>
			<Where Type="CIVILIZATION_SWEDEN"/>
			<Set AIPlayable="false" Playable="false"/>
		</Update>
	</Civilizations>
</GameData>